{
  "pnls": [
    {
      "name": "KMD",
      "pnl": 0.0168,
      "pnl_value": 0.0258,
      "weight": 0.0098,
      "rank": 52,
      "atr": 0.0776,
      "score": 1,
      "status": "o"
    },
    {
      "name": "NEBL",
      "pnl": 0.0109,
      "pnl_value": 0.0154,
      "weight": 0.009,
      "rank": 165,
      "atr": 0.0848,
      "score": 2,
      "status": "o"
    },
    {
      "name": "DCR",
      "pnl": -0.0021,
      "pnl_value": -0.0036,
      "weight": 0.011,
      "rank": 28,
      "atr": 0.0694,
      "score": 1,
      "status": "o"
    },
    {
      "name": "RLC",
      "pnl": -0.0255,
      "pnl_value": -0.0405,
      "weight": 0.0101,
      "rank": 135,
      "atr": 0.0752,
      "score": 2,
      "status": "o"
    },
    {
      "name": "MCO",
      "pnl": "-",
      "pnl_value": "-",
      "weight": "-",
      "rank": "-",
      "atr": "-",
      "score": "-",
      "status": "-"
    },
    {
      "name": "SC",
      "pnl": "-",
      "pnl_value": "-",
      "weight": "-",
      "rank": "-",
      "atr": "-",
      "score": "-",
      "status": "-"
    },
    {
      "name": "SALT",
      "pnl": "-",
      "pnl_value": "-",
      "weight": "-",
      "rank": "-",
      "atr": "-",
      "score": "-",
      "status": "-"
    },
    {
      "name": "BTM",
      "pnl": "-",
      "pnl_value": "-",
      "weight": "-",
      "rank": "-",
      "atr": "-",
      "score": "-",
      "status": "-"
    },
    {
      "name": "GVT",
      "pnl": "-",
      "pnl_value": "-",
      "weight": "-",
      "rank": "-",
      "atr": "-",
      "score": "-",
      "status": "-"
    }
  ],
  "raw_selected": [
    {
      "name": "DCR",
      "rank": 28,
      "atr": 0.0694,
      "type": 0,
      "score": 1
    },
    {
      "name": "RLC",
      "rank": 135,
      "atr": 0.0752,
      "type": 1,
      "score": 1
    },
    {
      "name": "KMD",
      "rank": 52,
      "atr": 0.0776,
      "type": 0,
      "score": 1
    },
    {
      "name": "NEBL",
      "rank": 165,
      "atr": 0.0848,
      "type": 1,
      "score": 1
    }
  ],
  "summary": {
    "daily_pnl": -0.0,
    "cum_pnl": 155.8357,
    "leverage": 0.0399,
    "atr": 0.003,
    "marketcap_pnt": 0.0026,
    "green_marketcap_pnt": 0
  }
}