{
  "pnls": [
    {
      "name": "ONE",
      "pnl": 0.0342,
      "pnl_value": 0.004,
      "weight": 0.0861,
      "rank": 185,
      "atr": 0.106,
      "score": 1,
      "status": "o"
    },
    {
      "name": "REN",
      "pnl": -0.0618,
      "pnl_value": -0.0087,
      "weight": 0.1036,
      "rank": 96,
      "atr": 0.0881,
      "score": 1,
      "status": "o"
    },
    {
      "name": "ZRX",
      "pnl": -0.1313,
      "pnl_value": -0.0196,
      "weight": 0.1102,
      "rank": 38,
      "atr": 0.0828,
      "score": 1,
      "status": "o"
    },
    {
      "name": "IOTA",
      "pnl": "-",
      "pnl_value": "-",
      "weight": "-",
      "rank": "-",
      "atr": "-",
      "score": "-",
      "status": "-"
    },
    {
      "name": "TOMO",
      "pnl": "-",
      "pnl_value": "-",
      "weight": "-",
      "rank": "-",
      "atr": "-",
      "score": "-",
      "status": "-"
    },
    {
      "name": "BAT",
      "pnl": "-",
      "pnl_value": "-",
      "weight": "-",
      "rank": "-",
      "atr": "-",
      "score": "-",
      "status": "-"
    },
    {
      "name": "ICX",
      "pnl": "-",
      "pnl_value": "-",
      "weight": "-",
      "rank": "-",
      "atr": "-",
      "score": "-",
      "status": "-"
    },
    {
      "name": "NEO",
      "pnl": "-",
      "pnl_value": "-",
      "weight": "-",
      "rank": "-",
      "atr": "-",
      "score": "-",
      "status": "-"
    },
    {
      "name": "BCH",
      "pnl": "-",
      "pnl_value": "-",
      "weight": "-",
      "rank": "-",
      "atr": "-",
      "score": "-",
      "status": "-"
    }
  ],
  "raw_selected": [
    {
      "name": "ZRX",
      "rank": 38,
      "atr": 0.0828,
      "type": 0,
      "score": 1
    },
    {
      "name": "REN",
      "rank": 96,
      "atr": 0.0881,
      "type": 0,
      "score": 1
    },
    {
      "name": "ONE",
      "rank": 185,
      "atr": 0.106,
      "type": 0,
      "score": 1
    }
  ],
  "summary": {
    "daily_pnl": -0.0179,
    "cum_pnl": 0.3308,
    "leverage": 0.2999,
    "atr": 0.0274,
    "marketcap_pnt": 0.0014,
    "green_marketcap_pnt": 0
  }
}