{
  "pnls": [
    {
      "name": "SHIB",
      "pnl": 0.5766,
      "pnl_value": 0.5709,
      "weight": 0.0099,
      "rank": 47,
      "atr": 0.0947,
      "score": 1,
      "status": "o"
    },
    {
      "name": "LUNA",
      "pnl": 0.0945,
      "pnl_value": 0.0845,
      "weight": 0.009,
      "rank": 11,
      "atr": 0.1047,
      "score": 1,
      "status": "o"
    },
    {
      "name": "ICX",
      "pnl": 0.0051,
      "pnl_value": 0.0048,
      "weight": 0.0095,
      "rank": 74,
      "atr": 0.0987,
      "score": 1,
      "status": "+"
    },
    {
      "name": "OMG",
      "pnl": 0.0026,
      "pnl_value": 0.003,
      "weight": 0.0116,
      "rank": 56,
      "atr": 0.0808,
      "score": 1,
      "status": "o"
    },
    {
      "name": "AXS",
      "pnl": -0.0206,
      "pnl_value": -0.0267,
      "weight": 0.013,
      "rank": 23,
      "atr": 0.0723,
      "score": 1,
      "status": "o"
    },
    {
      "name": "REN",
      "pnl": -0.0395,
      "pnl_value": -0.0358,
      "weight": 0.0091,
      "rank": 86,
      "atr": 0.1034,
      "score": 1,
      "status": "o"
    },
    {
      "name": "XTZ",
      "pnl": -0.0404,
      "pnl_value": -0.0407,
      "weight": 0.0101,
      "rank": 24,
      "atr": 0.0929,
      "score": 1,
      "status": "+"
    },
    {
      "name": "AR",
      "pnl": -0.0767,
      "pnl_value": -0.0592,
      "weight": 0.0077,
      "rank": 63,
      "atr": 0.1213,
      "score": 1,
      "status": "+"
    }
  ],
  "raw_selected": [
    {
      "name": "AXS",
      "rank": 23,
      "atr": 0.0723,
      "type": 0,
      "score": 1
    },
    {
      "name": "OMG",
      "rank": 56,
      "atr": 0.0808,
      "type": 0,
      "score": 1
    },
    {
      "name": "XTZ",
      "rank": 24,
      "atr": 0.0929,
      "type": 0,
      "score": 1
    },
    {
      "name": "SHIB",
      "rank": 47,
      "atr": 0.0947,
      "type": 0,
      "score": 1
    },
    {
      "name": "ICX",
      "rank": 74,
      "atr": 0.0987,
      "type": 0,
      "score": 1
    },
    {
      "name": "REN",
      "rank": 86,
      "atr": 0.1034,
      "type": 0,
      "score": 1
    },
    {
      "name": "LUNA",
      "rank": 11,
      "atr": 0.1047,
      "type": 0,
      "score": 1
    },
    {
      "name": "AR",
      "rank": 63,
      "atr": 0.1213,
      "type": 0,
      "score": 1
    }
  ],
  "summary": {
    "daily_pnl": 0.005,
    "cum_pnl": 99.3033,
    "leverage": 0.0799,
    "atr": 0.0075,
    "marketcap_pnt": 0.0203,
    "green_marketcap_pnt": 0
  }
}