{
  "pnls": [],
  "raw_selected": [
    {
      "name": "EKT",
      "rank": 57,
      "atr": 0.0687,
      "type": 0,
      "score": 1
    },
    {
      "name": "KNC",
      "rank": 149,
      "atr": 0.0887,
      "type": 0,
      "score": 1
    },
    {
      "name": "KBC",
      "rank": 44,
      "atr": 0.1129,
      "type": 0,
      "score": 1
    }
  ],
  "summary": {
    "daily_pnl": 0.0,
    "cum_pnl": 180.3776,
    "leverage": 0.0,
    "atr": 0,
    "marketcap_pnt": 0,
    "green_marketcap_pnt": 0
  }
}