{
  "pnls": [
    {
      "name": "NEO",
      "pnl": 0.1534,
      "pnl_value": 5.0745,
      "weight": 0.0614,
      "rank": 22,
      "atr": 0.0542,
      "score": 1,
      "status": "o"
    },
    {
      "name": "QTUM",
      "pnl": 0.1043,
      "pnl_value": 2.6478,
      "weight": 0.0471,
      "rank": 53,
      "atr": 0.0707,
      "score": 1,
      "status": "o"
    },
    {
      "name": "XEM",
      "pnl": 0.0959,
      "pnl_value": 3.2408,
      "weight": 0.0627,
      "rank": 32,
      "atr": 0.0531,
      "score": 1,
      "status": "o"
    },
    {
      "name": "BAT",
      "pnl": 0.0562,
      "pnl_value": 1.5134,
      "weight": 0.05,
      "rank": 38,
      "atr": 0.0665,
      "score": 1,
      "status": "o"
    },
    {
      "name": "ZRX",
      "pnl": 0.0495,
      "pnl_value": 0.9876,
      "weight": 0.037,
      "rank": 41,
      "atr": 0.0898,
      "score": 1,
      "status": "o"
    },
    {
      "name": "OMG",
      "pnl": -0.0154,
      "pnl_value": -0.3876,
      "weight": 0.0468,
      "rank": 44,
      "atr": 0.0711,
      "score": 1,
      "status": "o"
    },
    {
      "name": "FXC",
      "pnl": -0.048,
      "pnl_value": -1.2238,
      "weight": 0.0473,
      "rank": 88,
      "atr": 0.0704,
      "score": 1,
      "status": "o"
    },
    {
      "name": "SNT",
      "pnl": -0.0493,
      "pnl_value": -1.2157,
      "weight": 0.0458,
      "rank": 102,
      "atr": 0.0727,
      "score": 1,
      "status": "o"
    },
    {
      "name": "REP",
      "pnl": -0.144,
      "pnl_value": -4.0047,
      "weight": 0.0516,
      "rank": 66,
      "atr": 0.0645,
      "score": 1,
      "status": "+"
    },
    {
      "name": "SC",
      "pnl": "-",
      "pnl_value": "-",
      "weight": "-",
      "rank": "-",
      "atr": "-",
      "score": "-",
      "status": "-"
    },
    {
      "name": "HMR",
      "pnl": "-",
      "pnl_value": "-",
      "weight": "-",
      "rank": "-",
      "atr": "-",
      "score": "-",
      "status": "-"
    },
    {
      "name": "NANO",
      "pnl": "-",
      "pnl_value": "-",
      "weight": "-",
      "rank": "-",
      "atr": "-",
      "score": "-",
      "status": "-"
    },
    {
      "name": "REN",
      "pnl": "-",
      "pnl_value": "-",
      "weight": "-",
      "rank": "-",
      "atr": "-",
      "score": "-",
      "status": "-"
    },
    {
      "name": "LTC",
      "pnl": "-",
      "pnl_value": "-",
      "weight": "-",
      "rank": "-",
      "atr": "-",
      "score": "-",
      "status": "-"
    },
    {
      "name": "TRX",
      "pnl": "-",
      "pnl_value": "-",
      "weight": "-",
      "rank": "-",
      "atr": "-",
      "score": "-",
      "status": "-"
    },
    {
      "name": "RSR",
      "pnl": "-",
      "pnl_value": "-",
      "weight": "-",
      "rank": "-",
      "atr": "-",
      "score": "-",
      "status": "-"
    }
  ],
  "raw_selected": [
    {
      "name": "XEM",
      "rank": 32,
      "atr": 0.0531,
      "type": 0,
      "score": 1
    },
    {
      "name": "NEO",
      "rank": 22,
      "atr": 0.0542,
      "type": 0,
      "score": 1
    },
    {
      "name": "REP",
      "rank": 66,
      "atr": 0.0645,
      "type": 0,
      "score": 1
    },
    {
      "name": "BAT",
      "rank": 38,
      "atr": 0.0665,
      "type": 0,
      "score": 1
    },
    {
      "name": "FXC",
      "rank": 88,
      "atr": 0.0704,
      "type": 0,
      "score": 1
    },
    {
      "name": "QTUM",
      "rank": 53,
      "atr": 0.0707,
      "type": 0,
      "score": 1
    },
    {
      "name": "OMG",
      "rank": 44,
      "atr": 0.0711,
      "type": 0,
      "score": 1
    },
    {
      "name": "SNT",
      "rank": 102,
      "atr": 0.0727,
      "type": 0,
      "score": 1
    },
    {
      "name": "ZRX",
      "rank": 41,
      "atr": 0.0898,
      "type": 0,
      "score": 1
    }
  ],
  "summary": {
    "daily_pnl": 0.0123,
    "cum_pnl": 544.477,
    "leverage": 0.4497,
    "atr": 0.03,
    "marketcap_pnt": 0.0102,
    "green_marketcap_pnt": 0
  }
}