{
  "pnls": [
    {
      "name": "BTM",
      "pnl": -0.035,
      "pnl_value": -0.0272,
      "weight": 0.0101,
      "rank": 42,
      "atr": 0.0908,
      "score": 2,
      "status": "o"
    }
  ],
  "raw_selected": [
    {
      "name": "BTM",
      "rank": 42,
      "atr": 0.0908,
      "type": 1,
      "score": 1
    }
  ],
  "summary": {
    "daily_pnl": -0.0004,
    "cum_pnl": 75.7947,
    "leverage": 0.0101,
    "atr": 0.0009,
    "marketcap_pnt": 0.0012,
    "green_marketcap_pnt": 0
  }
}