{
  "pnls": [
    {
      "name": "LTC",
      "pnl": -0.0339,
      "pnl_value": -0.0307,
      "weight": 0.0101,
      "rank": 7,
      "atr": 0.0547,
      "score": 2,
      "status": "+"
    }
  ],
  "raw_selected": [
    {
      "name": "LTC",
      "rank": 7,
      "atr": 0.0547,
      "type": 1,
      "score": 1
    }
  ],
  "summary": {
    "daily_pnl": -0.0003,
    "cum_pnl": 88.579,
    "leverage": 0.0101,
    "atr": 0.0006,
    "marketcap_pnt": 0.0169,
    "green_marketcap_pnt": 0
  }
}