{
  "pnls": [
    {
      "name": "OMG",
      "pnl": 0.4491,
      "pnl_value": 42.6081,
      "weight": 0.0856,
      "rank": 59,
      "atr": 0.0587,
      "score": 1,
      "status": "o"
    },
    {
      "name": "TRX",
      "pnl": 0.1208,
      "pnl_value": 14.3175,
      "weight": 0.1069,
      "rank": 16,
      "atr": 0.047,
      "score": 2,
      "status": "o"
    },
    {
      "name": "QTUM",
      "pnl": 0.0768,
      "pnl_value": 7.4882,
      "weight": 0.088,
      "rank": 54,
      "atr": 0.0571,
      "score": 1,
      "status": "o"
    },
    {
      "name": "LSK",
      "pnl": 0.0767,
      "pnl_value": 7.0129,
      "weight": 0.0825,
      "rank": 69,
      "atr": 0.0609,
      "score": 1,
      "status": "+"
    },
    {
      "name": "EOS",
      "pnl": 0.0444,
      "pnl_value": 4.8437,
      "weight": 0.0985,
      "rank": 12,
      "atr": 0.051,
      "score": 2,
      "status": "+"
    },
    {
      "name": "NEO",
      "pnl": 0.0265,
      "pnl_value": 3.1835,
      "weight": 0.1085,
      "rank": 25,
      "atr": 0.0463,
      "score": 2,
      "status": "o"
    },
    {
      "name": "CELO",
      "pnl": 0.0239,
      "pnl_value": 2.902,
      "weight": 0.1097,
      "rank": 58,
      "atr": 0.0458,
      "score": 1,
      "status": "o"
    },
    {
      "name": "MIOTA",
      "pnl": 0.011,
      "pnl_value": 1.3202,
      "weight": 0.1087,
      "rank": 23,
      "atr": 0.0462,
      "score": 2,
      "status": "o"
    },
    {
      "name": "ETH",
      "pnl": 0.0028,
      "pnl_value": 0.3776,
      "weight": 0.1208,
      "rank": 2,
      "atr": 0.0416,
      "score": 1,
      "status": "o"
    },
    {
      "name": "LINK",
      "pnl": -0.0203,
      "pnl_value": -2.0354,
      "weight": 0.0905,
      "rank": 6,
      "atr": 0.0555,
      "score": 2,
      "status": "o"
    },
    {
      "name": "DCR",
      "pnl": "-",
      "pnl_value": "-",
      "weight": "-",
      "rank": "-",
      "atr": "-",
      "score": "-",
      "status": "-"
    },
    {
      "name": "HYN",
      "pnl": "-",
      "pnl_value": "-",
      "weight": "-",
      "rank": "-",
      "atr": "-",
      "score": "-",
      "status": "-"
    }
  ],
  "raw_selected": [
    {
      "name": "ETH",
      "rank": 2,
      "atr": 0.0416,
      "type": 0,
      "score": 1
    },
    {
      "name": "CELO",
      "rank": 58,
      "atr": 0.0458,
      "type": 0,
      "score": 1
    },
    {
      "name": "MIOTA",
      "rank": 23,
      "atr": 0.0462,
      "type": 1,
      "score": 1
    },
    {
      "name": "NEO",
      "rank": 25,
      "atr": 0.0463,
      "type": 1,
      "score": 1
    },
    {
      "name": "TRX",
      "rank": 16,
      "atr": 0.047,
      "type": 1,
      "score": 1
    },
    {
      "name": "EOS",
      "rank": 12,
      "atr": 0.051,
      "type": 1,
      "score": 1
    },
    {
      "name": "LINK",
      "rank": 6,
      "atr": 0.0555,
      "type": 1,
      "score": 1
    },
    {
      "name": "QTUM",
      "rank": 54,
      "atr": 0.0571,
      "type": 0,
      "score": 1
    },
    {
      "name": "OMG",
      "rank": 59,
      "atr": 0.0587,
      "type": 0,
      "score": 1
    },
    {
      "name": "LSK",
      "rank": 69,
      "atr": 0.0609,
      "type": 0,
      "score": 1
    },
    {
      "name": "HBAR",
      "rank": 62,
      "atr": 0.0612,
      "type": 0,
      "score": 1
    },
    {
      "name": "BTT",
      "rank": 53,
      "atr": 0.0626,
      "type": 1,
      "score": 1
    },
    {
      "name": "BTG",
      "rank": 74,
      "atr": 0.0627,
      "type": 1,
      "score": 1
    },
    {
      "name": "KCS",
      "rank": 131,
      "atr": 0.0628,
      "type": 1,
      "score": 1
    },
    {
      "name": "AE",
      "rank": 171,
      "atr": 0.0633,
      "type": 1,
      "score": 1
    },
    {
      "name": "DGB",
      "rank": 37,
      "atr": 0.0647,
      "type": 1,
      "score": 1
    },
    {
      "name": "WAVES",
      "rank": 65,
      "atr": 0.0648,
      "type": 0,
      "score": 1
    },
    {
      "name": "HC",
      "rank": 155,
      "atr": 0.0648,
      "type": 1,
      "score": 1
    },
    {
      "name": "ATOM",
      "rank": 22,
      "atr": 0.0658,
      "type": 0,
      "score": 1
    },
    {
      "name": "ICX",
      "rank": 60,
      "atr": 0.0659,
      "type": 0,
      "score": 1
    },
    {
      "name": "RVN",
      "rank": 85,
      "atr": 0.0668,
      "type": 0,
      "score": 1
    },
    {
      "name": "KMD",
      "rank": 124,
      "atr": 0.0698,
      "type": 0,
      "score": 1
    },
    {
      "name": "CKB",
      "rank": 90,
      "atr": 0.0709,
      "type": 1,
      "score": 1
    },
    {
      "name": "HYN",
      "rank": 51,
      "atr": 0.0738,
      "type": 0,
      "score": 1
    },
    {
      "name": "SNX",
      "rank": 38,
      "atr": 0.0743,
      "type": 1,
      "score": 1
    },
    {
      "name": "ZRX",
      "rank": 47,
      "atr": 0.0743,
      "type": 0,
      "score": 1
    },
    {
      "name": "ALGO",
      "rank": 44,
      "atr": 0.078,
      "type": 0,
      "score": 1
    },
    {
      "name": "REN",
      "rank": 66,
      "atr": 0.0786,
      "type": 1,
      "score": 1
    },
    {
      "name": "ELF",
      "rank": 163,
      "atr": 0.0834,
      "type": 1,
      "score": 1
    },
    {
      "name": "ONE",
      "rank": 154,
      "atr": 0.0857,
      "type": 0,
      "score": 1
    },
    {
      "name": "KNC",
      "rank": 42,
      "atr": 0.0869,
      "type": 0,
      "score": 1
    },
    {
      "name": "BTM",
      "rank": 95,
      "atr": 0.0911,
      "type": 0,
      "score": 1
    },
    {
      "name": "LRC",
      "rank": 79,
      "atr": 0.0939,
      "type": 0,
      "score": 1
    },
    {
      "name": "OGN",
      "rank": 194,
      "atr": 0.1001,
      "type": 0,
      "score": 1
    },
    {
      "name": "SXP",
      "rank": 84,
      "atr": 0.1059,
      "type": 0,
      "score": 1
    },
    {
      "name": "IRIS",
      "rank": 172,
      "atr": 0.1066,
      "type": 0,
      "score": 1
    },
    {
      "name": "RLC",
      "rank": 93,
      "atr": 0.1144,
      "type": 1,
      "score": 1
    },
    {
      "name": "COMP",
      "rank": 34,
      "atr": 0.1406,
      "type": 1,
      "score": 1
    }
  ],
  "summary": {
    "daily_pnl": 0.074,
    "cum_pnl": 1189.376,
    "leverage": 0.9997,
    "atr": 0.0502,
    "marketcap_pnt": 0.1558,
    "green_marketcap_pnt": 0
  }
}