{
  "pnls": [
    {
      "name": "UNI",
      "pnl": 0.0103,
      "pnl_value": 121.26,
      "weight": 0.0791,
      "rank": 12,
      "atr": 0.0933,
      "score": 1,
      "status": "o"
    },
    {
      "name": "BNB",
      "pnl": 0.0076,
      "pnl_value": 125.3935,
      "weight": 0.1113,
      "rank": 3,
      "atr": 0.0663,
      "score": 1,
      "status": "+"
    },
    {
      "name": "ETH",
      "pnl": 0.0034,
      "pnl_value": 56.5423,
      "weight": 0.113,
      "rank": 2,
      "atr": 0.0653,
      "score": 1,
      "status": "o"
    },
    {
      "name": "AXS",
      "pnl": -0.0158,
      "pnl_value": -202.7518,
      "weight": 0.0859,
      "rank": 23,
      "atr": 0.0859,
      "score": 1,
      "status": "o"
    },
    {
      "name": "CRO",
      "pnl": -0.016,
      "pnl_value": -257.8034,
      "weight": 0.1082,
      "rank": 37,
      "atr": 0.0682,
      "score": 1,
      "status": "o"
    },
    {
      "name": "QTUM",
      "pnl": -0.0287,
      "pnl_value": -373.8942,
      "weight": 0.0875,
      "rank": 76,
      "atr": 0.0843,
      "score": 1,
      "status": "o"
    },
    {
      "name": "CEL",
      "pnl": -0.034,
      "pnl_value": -660.7403,
      "weight": 0.1306,
      "rank": 79,
      "atr": 0.0565,
      "score": 1,
      "status": "+"
    },
    {
      "name": "XDC",
      "pnl": -0.0483,
      "pnl_value": -551.2718,
      "weight": 0.0766,
      "rank": 70,
      "atr": 0.0963,
      "score": 1,
      "status": "o"
    },
    {
      "name": "HNT",
      "pnl": -0.0568,
      "pnl_value": -682.2683,
      "weight": 0.0806,
      "rank": 58,
      "atr": 0.0915,
      "score": 1,
      "status": "+"
    },
    {
      "name": "SHIB",
      "pnl": -0.1812,
      "pnl_value": -3422.7231,
      "weight": 0.1268,
      "rank": 47,
      "atr": 0.0582,
      "score": 1,
      "status": "o"
    },
    {
      "name": "ICX",
      "pnl": "-",
      "pnl_value": "-",
      "weight": "-",
      "rank": "-",
      "atr": "-",
      "score": "-",
      "status": "-"
    },
    {
      "name": "LUNA",
      "pnl": "-",
      "pnl_value": "-",
      "weight": "-",
      "rank": "-",
      "atr": "-",
      "score": "-",
      "status": "-"
    },
    {
      "name": "OMG",
      "pnl": "-",
      "pnl_value": "-",
      "weight": "-",
      "rank": "-",
      "atr": "-",
      "score": "-",
      "status": "-"
    }
  ],
  "raw_selected": [
    {
      "name": "CEL",
      "rank": 79,
      "atr": 0.0565,
      "type": 0,
      "score": 1
    },
    {
      "name": "SHIB",
      "rank": 47,
      "atr": 0.0582,
      "type": 0,
      "score": 1
    },
    {
      "name": "ETH",
      "rank": 2,
      "atr": 0.0653,
      "type": 0,
      "score": 1
    },
    {
      "name": "BNB",
      "rank": 3,
      "atr": 0.0663,
      "type": 0,
      "score": 1
    },
    {
      "name": "CRO",
      "rank": 37,
      "atr": 0.0682,
      "type": 0,
      "score": 1
    },
    {
      "name": "QTUM",
      "rank": 76,
      "atr": 0.0843,
      "type": 0,
      "score": 1
    },
    {
      "name": "AXS",
      "rank": 23,
      "atr": 0.0859,
      "type": 0,
      "score": 1
    },
    {
      "name": "HNT",
      "rank": 58,
      "atr": 0.0915,
      "type": 0,
      "score": 1
    },
    {
      "name": "UNI",
      "rank": 12,
      "atr": 0.0933,
      "type": 0,
      "score": 1
    },
    {
      "name": "XDC",
      "rank": 70,
      "atr": 0.0963,
      "type": 0,
      "score": 1
    },
    {
      "name": "OMG",
      "rank": 56,
      "atr": 0.097,
      "type": 0,
      "score": 1
    },
    {
      "name": "ICX",
      "rank": 74,
      "atr": 0.0981,
      "type": 0,
      "score": 1
    },
    {
      "name": "AR",
      "rank": 63,
      "atr": 0.1035,
      "type": 0,
      "score": 1
    },
    {
      "name": "LUNA",
      "rank": 11,
      "atr": 0.1055,
      "type": 0,
      "score": 1
    },
    {
      "name": "XTZ",
      "rank": 24,
      "atr": 0.1058,
      "type": 0,
      "score": 1
    },
    {
      "name": "REN",
      "rank": 86,
      "atr": 0.1087,
      "type": 0,
      "score": 1
    },
    {
      "name": "CRV",
      "rank": 88,
      "atr": 0.1156,
      "type": 0,
      "score": 1
    },
    {
      "name": "ONE",
      "rank": 62,
      "atr": 0.1257,
      "type": 0,
      "score": 1
    }
  ],
  "summary": {
    "daily_pnl": -0.0393,
    "cum_pnl": 143146.1692,
    "leverage": 0.9996,
    "atr": 0.0738,
    "marketcap_pnt": 0.2414,
    "green_marketcap_pnt": 0
  }
}