{
  "pnls": [
    {
      "name": "PZM",
      "pnl_rate": 0.0408,
      "weight": 0.1071,
      "rank": 38,
      "atr": 0.0746
    },
    {
      "name": "ATOM",
      "pnl_rate": 0.0352,
      "weight": 0.1035,
      "rank": 20,
      "atr": 0.0758
    },
    {
      "name": "DOGE",
      "pnl_rate": 0.0343,
      "weight": 0.0461,
      "rank": 31,
      "atr": 0.1244
    },
    {
      "name": "MKR",
      "pnl_rate": 0.0298,
      "weight": 0.1023,
      "rank": 25,
      "atr": 0.0774
    },
    {
      "name": "BAT",
      "pnl_rate": 0.0234,
      "weight": 0.0798,
      "rank": 30,
      "atr": 0.0827
    },
    {
      "name": "XRP",
      "pnl_rate": 0.0149,
      "weight": 0.14,
      "rank": 3,
      "atr": 0.0572
    },
    {
      "name": "HOT",
      "pnl_rate": 0.0113,
      "weight": 0.1059,
      "rank": 45,
      "atr": 0.0763
    },
    {
      "name": "HEDG",
      "pnl_rate": 0.0,
      "weight": 0.0,
      "rank": 35,
      "atr": 0.0686
    },
    {
      "name": "LINK",
      "pnl_rate": -0.023,
      "weight": 0.0823,
      "rank": 15,
      "atr": 0.0836
    },
    {
      "name": "ABBC",
      "pnl_rate": -0.0315,
      "weight": 0.048,
      "rank": 43,
      "atr": 0.1353
    }
  ],
  "summary": {
    "rate": 0.0017,
    "value": 0.0608
  },
  "raw_selected": [
    {
      "name": "XRP",
      "rank": 3,
      "atr": 0.0587
    },
    {
      "name": "PZM",
      "rank": 42,
      "atr": 0.0767
    },
    {
      "name": "HOT",
      "rank": 46,
      "atr": 0.0776
    },
    {
      "name": "ATOM",
      "rank": 21,
      "atr": 0.0794
    },
    {
      "name": "MKR",
      "rank": 24,
      "atr": 0.0803
    },
    {
      "name": "LINK",
      "rank": 15,
      "atr": 0.0832
    },
    {
      "name": "BAT",
      "rank": 31,
      "atr": 0.0854
    },
    {
      "name": "ABBC",
      "rank": 39,
      "atr": 0.1275
    },
    {
      "name": "DOGE",
      "rank": 29,
      "atr": 0.1314
    },
    {
      "name": "HEDG",
      "rank": 35,
      "atr": 0.069
    },
    {
      "name": "ZRX",
      "rank": 36,
      "atr": 0.0856
    },
    {
      "name": "CENNZ",
      "rank": 51,
      "atr": 0.1536
    }
  ]
}