{
  "pnls": [],
  "raw_selected": [
    {
      "name": "PAX",
      "rank": 77,
      "atr": 0.0721,
      "type": 0,
      "score": 1
    },
    {
      "name": "LEO",
      "rank": 45,
      "atr": 0.0728,
      "type": 0,
      "score": 1
    },
    {
      "name": "CEL",
      "rank": 56,
      "atr": 0.0844,
      "type": 0,
      "score": 1
    },
    {
      "name": "KCS",
      "rank": 97,
      "atr": 0.0875,
      "type": 0,
      "score": 1
    },
    {
      "name": "STX",
      "rank": 70,
      "atr": 0.1069,
      "type": 0,
      "score": 1
    },
    {
      "name": "COMP",
      "rank": 43,
      "atr": 0.1364,
      "type": 0,
      "score": 1
    }
  ],
  "summary": {
    "daily_pnl": 0.0,
    "cum_pnl": 25166.1657,
    "leverage": 0.0,
    "atr": 0,
    "marketcap_pnt": 0,
    "green_marketcap_pnt": 0
  }
}