{
  "pnls": [
    {
      "name": "BTS",
      "pnl": 0.0493,
      "pnl_value": 0.0567,
      "weight": 0.0824,
      "rank": 8,
      "atr": 0.125,
      "score": 1,
      "status": "o"
    },
    {
      "name": "ZEC",
      "pnl": 0.0258,
      "pnl_value": 0.0271,
      "weight": 0.0755,
      "rank": 14,
      "atr": 0.1365,
      "score": 2,
      "status": "o"
    },
    {
      "name": "DASH",
      "pnl": 0.0038,
      "pnl_value": 0.0057,
      "weight": 0.1072,
      "rank": 7,
      "atr": 0.0961,
      "score": 1,
      "status": "o"
    },
    {
      "name": "ETH",
      "pnl": 0.0024,
      "pnl_value": 0.0046,
      "weight": 0.136,
      "rank": 2,
      "atr": 0.0758,
      "score": 1,
      "status": "o"
    },
    {
      "name": "ARDR",
      "pnl": -0.0032,
      "pnl_value": -0.0048,
      "weight": 0.1088,
      "rank": 30,
      "atr": 0.0947,
      "score": 2,
      "status": "o"
    },
    {
      "name": "POT",
      "pnl": -0.0722,
      "pnl_value": -0.0904,
      "weight": 0.0898,
      "rank": 88,
      "atr": 0.1147,
      "score": 1,
      "status": "o"
    },
    {
      "name": "BLK",
      "pnl": "-",
      "pnl_value": "-",
      "weight": "-",
      "rank": "-",
      "atr": "-",
      "score": "-",
      "status": "-"
    },
    {
      "name": "NEO",
      "pnl": "-",
      "pnl_value": "-",
      "weight": "-",
      "rank": "-",
      "atr": "-",
      "score": "-",
      "status": "-"
    },
    {
      "name": "FTC",
      "pnl": "-",
      "pnl_value": "-",
      "weight": "-",
      "rank": "-",
      "atr": "-",
      "score": "-",
      "status": "-"
    }
  ],
  "raw_selected": [
    {
      "name": "ETH",
      "rank": 2,
      "atr": 0.0758,
      "type": 0,
      "score": 1
    },
    {
      "name": "ARDR",
      "rank": 30,
      "atr": 0.0947,
      "type": 1,
      "score": 1
    },
    {
      "name": "DASH",
      "rank": 7,
      "atr": 0.0961,
      "type": 0,
      "score": 1
    },
    {
      "name": "POT",
      "rank": 88,
      "atr": 0.1147,
      "type": 0,
      "score": 1
    },
    {
      "name": "BTS",
      "rank": 8,
      "atr": 0.125,
      "type": 0,
      "score": 1
    },
    {
      "name": "ZEC",
      "rank": 14,
      "atr": 0.1365,
      "type": 1,
      "score": 1
    }
  ],
  "summary": {
    "daily_pnl": -0.0001,
    "cum_pnl": 12.9417,
    "leverage": 0.5997,
    "atr": 0.0618,
    "marketcap_pnt": 0.3084,
    "green_marketcap_pnt": 0
  }
}