{
  "pnls": [
    {
      "name": "TWT",
      "pnl": 0.1057,
      "pnl_value": 0.185,
      "weight": 0.01,
      "rank": 182,
      "atr": 0.0897,
      "score": 2,
      "status": "+"
    },
    {
      "name": "KNC",
      "pnl": 0.0877,
      "pnl_value": 0.155,
      "weight": 0.0101,
      "rank": 120,
      "atr": 0.0889,
      "score": 2,
      "status": "o"
    },
    {
      "name": "BAT",
      "pnl": -0.0101,
      "pnl_value": -0.0188,
      "weight": 0.0106,
      "rank": 76,
      "atr": 0.0842,
      "score": 2,
      "status": "+"
    },
    {
      "name": "XNO",
      "pnl": -0.1046,
      "pnl_value": -0.1683,
      "weight": 0.0092,
      "rank": 180,
      "atr": 0.0976,
      "score": 2,
      "status": "+"
    }
  ],
  "raw_selected": [
    {
      "name": "BAT",
      "rank": 76,
      "atr": 0.0842,
      "type": 1,
      "score": 1
    },
    {
      "name": "KNC",
      "rank": 120,
      "atr": 0.0889,
      "type": 1,
      "score": 1
    },
    {
      "name": "TWT",
      "rank": 182,
      "atr": 0.0897,
      "type": 1,
      "score": 1
    },
    {
      "name": "XNO",
      "rank": 180,
      "atr": 0.0976,
      "type": 1,
      "score": 1
    }
  ],
  "summary": {
    "daily_pnl": 0.0009,
    "cum_pnl": 174.0768,
    "leverage": 0.0399,
    "atr": 0.0036,
    "marketcap_pnt": 0.0011,
    "green_marketcap_pnt": 0
  }
}