{
  "pnls": [
    {
      "name": "AMPL",
      "pnl": 0.0594,
      "pnl_value": 7.1231,
      "weight": 0.0525,
      "rank": 84,
      "atr": 0.1479,
      "score": 1,
      "status": "o"
    },
    {
      "name": "DCR",
      "pnl": 0.0471,
      "pnl_value": 13.5859,
      "weight": 0.1263,
      "rank": 70,
      "atr": 0.0615,
      "score": 1,
      "status": "o"
    },
    {
      "name": "CEL",
      "pnl": 0.0458,
      "pnl_value": 12.6736,
      "weight": 0.1211,
      "rank": 42,
      "atr": 0.0641,
      "score": 1,
      "status": "o"
    }
  ],
  "raw_selected": [
    {
      "name": "DCR",
      "rank": 70,
      "atr": 0.0615,
      "type": 0,
      "score": 1
    },
    {
      "name": "CEL",
      "rank": 42,
      "atr": 0.0641,
      "type": 0,
      "score": 1
    },
    {
      "name": "AMPL",
      "rank": 84,
      "atr": 0.1479,
      "type": 0,
      "score": 1
    }
  ],
  "summary": {
    "daily_pnl": 0.0146,
    "cum_pnl": 2315.3965,
    "leverage": 0.2999,
    "atr": 0.0233,
    "marketcap_pnt": 0.0015,
    "green_marketcap_pnt": 0
  }
}