{
  "pnls": [
    {
      "name": "KSM",
      "pnl": 0.326,
      "pnl_value": 4.4187,
      "weight": 0.0195,
      "rank": 64,
      "atr": 0.0849,
      "score": 2,
      "status": "o"
    },
    {
      "name": "AMPL",
      "pnl": 0.2098,
      "pnl_value": 1.1956,
      "weight": 0.0082,
      "rank": 63,
      "atr": 0.2006,
      "score": 2,
      "status": "+"
    },
    {
      "name": "COMP",
      "pnl": 0.1202,
      "pnl_value": 1.2862,
      "weight": 0.0154,
      "rank": 36,
      "atr": 0.1075,
      "score": 2,
      "status": "+"
    },
    {
      "name": "YFI",
      "pnl": 0.1047,
      "pnl_value": 1.7243,
      "weight": 0.0237,
      "rank": 25,
      "atr": 0.0697,
      "score": 2,
      "status": "+"
    },
    {
      "name": "SOL",
      "pnl": 0.0882,
      "pnl_value": 1.1038,
      "weight": 0.018,
      "rank": 105,
      "atr": 0.0916,
      "score": 2,
      "status": "o"
    },
    {
      "name": "SNX",
      "pnl": 0.0029,
      "pnl_value": 0.037,
      "weight": 0.0185,
      "rank": 33,
      "atr": 0.0891,
      "score": 2,
      "status": "+"
    },
    {
      "name": "FTT",
      "pnl": 0.0,
      "pnl_value": 0.0,
      "weight": 0.0516,
      "rank": 48,
      "atr": 0.0321,
      "score": 2,
      "status": "o"
    },
    {
      "name": "NEO",
      "pnl": -0.0111,
      "pnl_value": -0.2172,
      "weight": 0.0281,
      "rank": 19,
      "atr": 0.0588,
      "score": 1,
      "status": "o"
    },
    {
      "name": "CELO",
      "pnl": -0.0439,
      "pnl_value": -0.2534,
      "weight": 0.0083,
      "rank": 37,
      "atr": 0.1974,
      "score": 2,
      "status": "o"
    },
    {
      "name": "STORJ",
      "pnl": -0.059,
      "pnl_value": -0.5209,
      "weight": 0.0127,
      "rank": 116,
      "atr": 0.1303,
      "score": 1,
      "status": "+"
    },
    {
      "name": "LRC",
      "pnl": -0.0651,
      "pnl_value": -0.9046,
      "weight": 0.02,
      "rank": 66,
      "atr": 0.0828,
      "score": 2,
      "status": "+"
    },
    {
      "name": "SC",
      "pnl": "-",
      "pnl_value": "-",
      "weight": "-",
      "rank": "-",
      "atr": "-",
      "score": "-",
      "status": "-"
    }
  ],
  "raw_selected": [
    {
      "name": "FTT",
      "rank": 48,
      "atr": 0.0321,
      "type": 1,
      "score": 1
    },
    {
      "name": "NEO",
      "rank": 19,
      "atr": 0.0588,
      "type": 0,
      "score": 1
    },
    {
      "name": "YFI",
      "rank": 25,
      "atr": 0.0697,
      "type": 1,
      "score": 1
    },
    {
      "name": "LRC",
      "rank": 66,
      "atr": 0.0828,
      "type": 1,
      "score": 1
    },
    {
      "name": "KSM",
      "rank": 64,
      "atr": 0.0849,
      "type": 1,
      "score": 1
    },
    {
      "name": "SNX",
      "rank": 33,
      "atr": 0.0891,
      "type": 1,
      "score": 1
    },
    {
      "name": "SOL",
      "rank": 105,
      "atr": 0.0916,
      "type": 1,
      "score": 1
    },
    {
      "name": "COMP",
      "rank": 36,
      "atr": 0.1075,
      "type": 1,
      "score": 1
    },
    {
      "name": "STORJ",
      "rank": 116,
      "atr": 0.1303,
      "type": 0,
      "score": 1
    },
    {
      "name": "CELO",
      "rank": 37,
      "atr": 0.1974,
      "type": 1,
      "score": 1
    },
    {
      "name": "AMPL",
      "rank": 63,
      "atr": 0.2006,
      "type": 1,
      "score": 1
    }
  ],
  "summary": {
    "daily_pnl": 0.0113,
    "cum_pnl": 701.8781,
    "leverage": 0.224,
    "atr": 0.0182,
    "marketcap_pnt": 0.0153,
    "green_marketcap_pnt": 0
  }
}