{
  "pnls": [
    {
      "name": "LEO",
      "pnl": 0.2544,
      "pnl_value": 117.2339,
      "weight": 0.0127,
      "rank": 36,
      "atr": 0.0464,
      "score": 1,
      "status": "o"
    },
    {
      "name": "FTT",
      "pnl": 0.0777,
      "pnl_value": 20.2911,
      "weight": 0.0072,
      "rank": 27,
      "atr": 0.0822,
      "score": 1,
      "status": "o"
    },
    {
      "name": "CHSB",
      "pnl": "-",
      "pnl_value": "-",
      "weight": "-",
      "rank": "-",
      "atr": "-",
      "score": "-",
      "status": "-"
    }
  ],
  "raw_selected": [
    {
      "name": "LEO",
      "rank": 36,
      "atr": 0.0464,
      "type": 0,
      "score": 1
    },
    {
      "name": "FTT",
      "rank": 27,
      "atr": 0.0822,
      "type": 0,
      "score": 1
    }
  ],
  "summary": {
    "daily_pnl": 0.0038,
    "cum_pnl": 36425.1953,
    "leverage": 0.0199,
    "atr": 0.0012,
    "marketcap_pnt": 0.0054,
    "green_marketcap_pnt": 0
  }
}