{
  "pnls": [
    {
      "name": "REN",
      "pnl_rate": 0.2229,
      "weight": 0.0802,
      "rank": 115,
      "atr": 0.075
    },
    {
      "name": "MATIC",
      "pnl_rate": 0.0725,
      "weight": 0.0797,
      "rank": 111,
      "atr": 0.0844
    },
    {
      "name": "THETA",
      "pnl_rate": 0.0029,
      "weight": 0.0532,
      "rank": 66,
      "atr": 0.103
    },
    {
      "name": "ETH",
      "pnl_rate": -0.0314,
      "weight": 0.0924,
      "rank": 2,
      "atr": 0.0677
    },
    {
      "name": "TOMO",
      "pnl_rate": -0.0349,
      "weight": 0.0502,
      "rank": 147,
      "atr": 0.111
    },
    {
      "name": "HBAR",
      "pnl_rate": -0.0477,
      "weight": 0.0495,
      "rank": 62,
      "atr": 0.1185
    },
    {
      "name": "FTT",
      "pnl_rate": -0.0492,
      "weight": 0.0997,
      "rank": 36,
      "atr": 0.0727
    },
    {
      "name": "CHZ",
      "pnl_rate": -0.0502,
      "weight": 0.0515,
      "rank": 103,
      "atr": 0.1121
    },
    {
      "name": "XTZ",
      "pnl_rate": -0.0593,
      "weight": 0.0597,
      "rank": 10,
      "atr": 0.1006
    },
    {
      "name": "WAVES",
      "pnl_rate": -0.0687,
      "weight": 0.0711,
      "rank": 63,
      "atr": 0.0878
    },
    {
      "name": "LINK",
      "pnl_rate": -0.0715,
      "weight": 0.0917,
      "rank": 11,
      "atr": 0.0821
    },
    {
      "name": "ICX",
      "pnl_rate": -0.0797,
      "weight": 0.0478,
      "rank": 48,
      "atr": 0.1224
    },
    {
      "name": "ALGO",
      "pnl_rate": -0.0959,
      "weight": 0.0475,
      "rank": 43,
      "atr": 0.1258
    }
  ],
  "summary": {
    "rate": -0.0003,
    "value": -0.0003
  },
  "raw_selected": [
    {
      "name": "FTT",
      "rank": 36,
      "atr": 0.0699
    },
    {
      "name": "LINK",
      "rank": 11,
      "atr": 0.076
    },
    {
      "name": "REN",
      "rank": 115,
      "atr": 0.0869
    },
    {
      "name": "MATIC",
      "rank": 111,
      "atr": 0.0875
    },
    {
      "name": "ETH",
      "rank": 2,
      "atr": 0.0656
    },
    {
      "name": "WAVES",
      "rank": 63,
      "atr": 0.082
    },
    {
      "name": "XTZ",
      "rank": 10,
      "atr": 0.0947
    },
    {
      "name": "THETA",
      "rank": 66,
      "atr": 0.1038
    },
    {
      "name": "CHZ",
      "rank": 103,
      "atr": 0.1065
    },
    {
      "name": "TOMO",
      "rank": 147,
      "atr": 0.1088
    },
    {
      "name": "HBAR",
      "rank": 62,
      "atr": 0.11
    },
    {
      "name": "ICX",
      "rank": 48,
      "atr": 0.113
    },
    {
      "name": "ALGO",
      "rank": 43,
      "atr": 0.1135
    }
  ]
}