{
  "pnls": [
    {
      "name": "MKR",
      "pnl": 0.2881,
      "pnl_value": 0.2981,
      "weight": 0.0087,
      "rank": 24,
      "atr": 0.0821,
      "score": 1,
      "status": "o"
    },
    {
      "name": "DCR",
      "pnl": 0.0976,
      "pnl_value": 0.1404,
      "weight": 0.0121,
      "rank": 29,
      "atr": 0.059,
      "score": 1,
      "status": "o"
    },
    {
      "name": "WAN",
      "pnl": 0.0332,
      "pnl_value": 0.0256,
      "weight": 0.0065,
      "rank": 59,
      "atr": 0.1102,
      "score": 2,
      "status": "o"
    },
    {
      "name": "SC",
      "pnl": 0.0123,
      "pnl_value": 0.0119,
      "weight": 0.0081,
      "rank": 35,
      "atr": 0.088,
      "score": 2,
      "status": "o"
    },
    {
      "name": "BNB",
      "pnl": -0.0028,
      "pnl_value": -0.005,
      "weight": 0.0148,
      "rank": 14,
      "atr": 0.0483,
      "score": 2,
      "status": "+"
    }
  ],
  "raw_selected": [
    {
      "name": "BNB",
      "rank": 14,
      "atr": 0.0483,
      "type": 1,
      "score": 1
    },
    {
      "name": "DCR",
      "rank": 29,
      "atr": 0.059,
      "type": 0,
      "score": 1
    },
    {
      "name": "MKR",
      "rank": 24,
      "atr": 0.0821,
      "type": 0,
      "score": 1
    },
    {
      "name": "SC",
      "rank": 35,
      "atr": 0.088,
      "type": 1,
      "score": 1
    },
    {
      "name": "WAN",
      "rank": 59,
      "atr": 0.1102,
      "type": 1,
      "score": 1
    }
  ],
  "summary": {
    "daily_pnl": 0.004,
    "cum_pnl": 118.3859,
    "leverage": 0.0502,
    "atr": 0.0036,
    "marketcap_pnt": 0.0113,
    "green_marketcap_pnt": 0
  }
}