{
  "pnls": [
    {
      "name": "ADA",
      "pnl": 0.193,
      "pnl_value": 2.6555,
      "weight": 0.0254,
      "rank": 11,
      "atr": 0.0582,
      "score": 1,
      "status": "o"
    },
    {
      "name": "BAND",
      "pnl": 0.1506,
      "pnl_value": 1.0034,
      "weight": 0.0123,
      "rank": 191,
      "atr": 0.1202,
      "score": 2,
      "status": "o"
    },
    {
      "name": "VET",
      "pnl": 0.125,
      "pnl_value": 1.158,
      "weight": 0.0171,
      "rank": 40,
      "atr": 0.0867,
      "score": 2,
      "status": "o"
    },
    {
      "name": "ETH",
      "pnl": 0.1044,
      "pnl_value": 1.9115,
      "weight": 0.0338,
      "rank": 2,
      "atr": 0.0438,
      "score": 2,
      "status": "o"
    },
    {
      "name": "ONT",
      "pnl": 0.0987,
      "pnl_value": 1.3417,
      "weight": 0.0251,
      "rank": 33,
      "atr": 0.0589,
      "score": 1,
      "status": "o"
    },
    {
      "name": "ZIL",
      "pnl": 0.0815,
      "pnl_value": 0.6575,
      "weight": 0.0149,
      "rank": 73,
      "atr": 0.099,
      "score": 1,
      "status": "o"
    },
    {
      "name": "QTUM",
      "pnl": 0.0667,
      "pnl_value": 0.8859,
      "weight": 0.0245,
      "rank": 53,
      "atr": 0.0605,
      "score": 2,
      "status": "+"
    },
    {
      "name": "ALGO",
      "pnl": 0.0666,
      "pnl_value": 0.6673,
      "weight": 0.0185,
      "rank": 59,
      "atr": 0.0801,
      "score": 2,
      "status": "o"
    },
    {
      "name": "ETN",
      "pnl": 0.0495,
      "pnl_value": 0.3885,
      "weight": 0.0145,
      "rank": 90,
      "atr": 0.1022,
      "score": 1,
      "status": "o"
    },
    {
      "name": "ETC",
      "pnl": 0.0379,
      "pnl_value": 0.5366,
      "weight": 0.0261,
      "rank": 19,
      "atr": 0.0567,
      "score": 2,
      "status": "+"
    },
    {
      "name": "MKR",
      "pnl": 0.0321,
      "pnl_value": 0.3865,
      "weight": 0.0222,
      "rank": 32,
      "atr": 0.0666,
      "score": 2,
      "status": "+"
    },
    {
      "name": "NEXO",
      "pnl": 0.0239,
      "pnl_value": 0.3315,
      "weight": 0.0256,
      "rank": 106,
      "atr": 0.0579,
      "score": 2,
      "status": "o"
    },
    {
      "name": "HBAR",
      "pnl": 0.0167,
      "pnl_value": 0.1391,
      "weight": 0.0154,
      "rank": 50,
      "atr": 0.0957,
      "score": 1,
      "status": "o"
    },
    {
      "name": "NULS",
      "pnl": 0.0137,
      "pnl_value": 0.1481,
      "weight": 0.02,
      "rank": 194,
      "atr": 0.074,
      "score": 2,
      "status": "o"
    },
    {
      "name": "CTXC",
      "pnl": 0.0115,
      "pnl_value": 0.0927,
      "weight": 0.0149,
      "rank": 193,
      "atr": 0.0995,
      "score": 1,
      "status": "o"
    },
    {
      "name": "ENJ",
      "pnl": 0.004,
      "pnl_value": 0.0358,
      "weight": 0.0167,
      "rank": 61,
      "atr": 0.0883,
      "score": 1,
      "status": "o"
    },
    {
      "name": "BNT",
      "pnl": -0.02,
      "pnl_value": -0.1937,
      "weight": 0.0179,
      "rank": 174,
      "atr": 0.0825,
      "score": 1,
      "status": "o"
    },
    {
      "name": "ELA",
      "pnl": -0.0694,
      "pnl_value": -0.5114,
      "weight": 0.0136,
      "rank": 181,
      "atr": 0.1083,
      "score": 2,
      "status": "+"
    },
    {
      "name": "MATIC",
      "pnl": -0.0718,
      "pnl_value": -0.8009,
      "weight": 0.0206,
      "rank": 99,
      "atr": 0.0718,
      "score": 2,
      "status": "o"
    }
  ],
  "raw_selected": [
    {
      "name": "ETH",
      "rank": 2,
      "atr": 0.0438,
      "type": 1,
      "score": 1
    },
    {
      "name": "ETC",
      "rank": 19,
      "atr": 0.0567,
      "type": 1,
      "score": 1
    },
    {
      "name": "NEXO",
      "rank": 106,
      "atr": 0.0579,
      "type": 1,
      "score": 1
    },
    {
      "name": "ADA",
      "rank": 11,
      "atr": 0.0582,
      "type": 0,
      "score": 1
    },
    {
      "name": "ONT",
      "rank": 33,
      "atr": 0.0589,
      "type": 0,
      "score": 1
    },
    {
      "name": "QTUM",
      "rank": 53,
      "atr": 0.0605,
      "type": 1,
      "score": 1
    },
    {
      "name": "MKR",
      "rank": 32,
      "atr": 0.0666,
      "type": 1,
      "score": 1
    },
    {
      "name": "MATIC",
      "rank": 99,
      "atr": 0.0718,
      "type": 1,
      "score": 1
    },
    {
      "name": "NULS",
      "rank": 194,
      "atr": 0.074,
      "type": 1,
      "score": 1
    },
    {
      "name": "ALGO",
      "rank": 59,
      "atr": 0.0801,
      "type": 1,
      "score": 1
    },
    {
      "name": "BNT",
      "rank": 174,
      "atr": 0.0825,
      "type": 0,
      "score": 1
    },
    {
      "name": "VET",
      "rank": 40,
      "atr": 0.0867,
      "type": 1,
      "score": 1
    },
    {
      "name": "ENJ",
      "rank": 61,
      "atr": 0.0883,
      "type": 0,
      "score": 1
    },
    {
      "name": "HBAR",
      "rank": 50,
      "atr": 0.0957,
      "type": 0,
      "score": 1
    },
    {
      "name": "ZIL",
      "rank": 73,
      "atr": 0.099,
      "type": 0,
      "score": 1
    },
    {
      "name": "CTXC",
      "rank": 193,
      "atr": 0.0995,
      "type": 0,
      "score": 1
    },
    {
      "name": "ETN",
      "rank": 90,
      "atr": 0.1022,
      "type": 0,
      "score": 1
    },
    {
      "name": "ELA",
      "rank": 181,
      "atr": 0.1083,
      "type": 1,
      "score": 1
    },
    {
      "name": "BAND",
      "rank": 191,
      "atr": 0.1202,
      "type": 1,
      "score": 1
    }
  ],
  "summary": {
    "daily_pnl": 0.02,
    "cum_pnl": 551.6061,
    "leverage": 0.3791,
    "atr": 0.0281,
    "marketcap_pnt": 0.1067,
    "green_marketcap_pnt": 0
  }
}